{
  "modules": {
    "numpy": {
      "function_overloads": {
        "arange": [
          {
            "pos_only_required": {
              "_0": {
                "type": {
                  "name": "int"
                }
              }
            },
            "metadata": {
              "usage.sample-usage": 4
            }
          }
        ],
        "array": [
          {
            "pos_only_required": {
              "_0": {
                "type": "str",
                "options": [
                  "df"
                ]
              }
            },
            "metadata": {
              "usage.sample-usage": 1
            }
          },
          {
            "pos_only_required": {
              "_0": {
                "type": "str"
              }
            },
            "metadata": {
              "usage.sample-usage": 1
            }
          },
          {
            "pos_only_required": {
              "_0": {
                "type": "list",
                "item": {
                  "type": {
                    "name": "int"
                  }
                }
              }
            },
            "metadata": {
              "usage.sample-usage": 1
            }
          }
        ],
        "zeros": [
          {
            "pos_only_required": {
              "_0": {
                "type": "tuple",
                "items": [
                  {
                    "type": {
                      "name": "int"
                    }
                  },
                  {
                    "type": {
                      "name": "int"
                    }
                  }
                ]
              }
            },
            "metadata": {
              "usage.sample-usage": 1
            }
          }
        ],
        "ones": [
          {
            "pos_or_kw_required": {
              "shape": {
                "type": "tuple",
                "items": [
                  {
                    "type": {
                      "name": "int"
                    }
                  },
                  {
                    "type": {
                      "name": "int"
                    }
                  }
                ]
              }
            },
            "metadata": {
              "usage.sample-usage": 1
            }
          }
        ],
        "linspace": [
          {
            "pos_or_kw_required": {
              "start": {
                "type": {
                  "name": "int"
                }
              },
              "stop": {
                "type": {
                  "name": "int"
                }
              },
              "num": {
                "type": {
                  "name": "int"
                }
              }
            },
            "metadata": {
              "usage.sample-usage": 1
            }
          }
        ],
        "eye": [
          {
            "pos_or_kw_required": {
              "N": {
                "type": {
                  "name": "int"
                }
              }
            },
            "metadata": {
              "usage.sample-usage": 1
            }
          }
        ],
        "column_stack": [
          {
            "pos_or_kw_required": {
              "tup": {
                "type": "list",
                "item": {
                  "type": {
                    "module": "numpy",
                    "name": "ndarray"
                  }
                }
              }
            },
            "metadata": {
              "usage.sample-usage": 1
            }
          }
        ],
        "concatenate": [
          {
            "pos_only_required": {
              "_0": {
                "type": "tuple",
                "items": [
                  {
                    "type": {
                      "module": "numpy",
                      "name": "ndarray"
                    }
                  },
                  {
                    "type": {
                      "module": "numpy",
                      "name": "ndarray"
                    }
                  }
                ]
              }
            },
            "kw_only_required": {
              "axis": {
                "type": {
                  "name": "int"
                }
              }
            },
            "metadata": {
              "usage.sample-usage": 1
            }
          }
        ]
      },
      "functions": {
        "arange": {
          "pos_only_required": {
            "_0": {
              "type": {
                "name": "int"
              }
            }
          },
          "metadata": {
            "usage.sample-usage": 4
          }
        },
        "array": {
          "pos_only_required": {
            "_0": {
              "type": "union",
              "options": [
                {
                  "type": "list",
                  "item": {
                    "type": {
                      "name": "int"
                    }
                  }
                },
                {
                  "type": "str"
                }
              ]
            }
          },
          "metadata": {
            "usage.sample-usage": 3
          }
        },
        "zeros": {
          "pos_only_required": {
            "_0": {
              "type": "tuple",
              "items": [
                {
                  "type": {
                    "name": "int"
                  }
                },
                {
                  "type": {
                    "name": "int"
                  }
                }
              ]
            }
          },
          "metadata": {
            "usage.sample-usage": 1
          }
        },
        "ones": {
          "pos_or_kw_required": {
            "shape": {
              "type": "tuple",
              "items": [
                {
                  "type": {
                    "name": "int"
                  }
                },
                {
                  "type": {
                    "name": "int"
                  }
                }
              ]
            }
          },
          "metadata": {
            "usage.sample-usage": 1
          }
        },
        "linspace": {
          "pos_or_kw_required": {
            "start": {
              "type": {
                "name": "int"
              }
            },
            "stop": {
              "type": {
                "name": "int"
              }
            },
            "num": {
              "type": {
                "name": "int"
              }
            }
          },
          "metadata": {
            "usage.sample-usage": 1
          }
        },
        "eye": {
          "pos_or_kw_required": {
            "N": {
              "type": {
                "name": "int"
              }
            }
          },
          "metadata": {
            "usage.sample-usage": 1
          }
        },
        "column_stack": {
          "pos_or_kw_required": {
            "tup": {
              "type": "list",
              "item": {
                "type": {
                  "module": "numpy",
                  "name": "ndarray"
                }
              }
            }
          },
          "metadata": {
            "usage.sample-usage": 1
          }
        },
        "concatenate": {
          "pos_only_required": {
            "_0": {
              "type": "tuple",
              "items": [
                {
                  "type": {
                    "module": "numpy",
                    "name": "ndarray"
                  }
                },
                {
                  "type": {
                    "module": "numpy",
                    "name": "ndarray"
                  }
                }
              ]
            }
          },
          "kw_only_required": {
            "axis": {
              "type": {
                "name": "int"
              }
            }
          },
          "metadata": {
            "usage.sample-usage": 1
          }
        }
      },
      "classes": {
        "ndarray": {
          "constructor_overloads": [
            {
              "pos_only_required": {
                "_0": {
                  "type": "tuple",
                  "items": [
                    {
                      "type": {
                        "name": "int"
                      }
                    },
                    {
                      "type": {
                        "name": "int"
                      }
                    },
                    {
                      "type": {
                        "name": "int"
                      }
                    }
                  ]
                }
              },
              "metadata": {
                "usage.sample-usage": 1
              }
            }
          ],
          "constructor": {
            "pos_only_required": {
              "_0": {
                "type": "tuple",
                "items": [
                  {
                    "type": {
                      "name": "int"
                    }
                  },
                  {
                    "type": {
                      "name": "int"
                    }
                  },
                  {
                    "type": {
                      "name": "int"
                    }
                  }
                ]
              }
            },
            "metadata": {
              "usage.sample-usage": 1
            }
          },
          "method_overloads": {
            "__pos__": [
              {
                "metadata": {
                  "usage.sample-usage": 1
                }
              }
            ],
            "__neg__": [
              {
                "metadata": {
                  "usage.sample-usage": 1
                }
              }
            ],
            "__invert__": [
              {
                "metadata": {
                  "usage.sample-usage": 1
                }
              }
            ],
            "__bool__": [
              {
                "metadata": {
                  "usage.sample-usage": 1
                }
              }
            ],
            "__iter__": [
              {
                "metadata": {
                  "usage.sample-usage": 2
                }
              }
            ],
            "__getitem__": [
              {
                "pos_only_required": {
                  "_0": {
                    "type": {
                      "name": "int"
                    }
                  }
                },
                "metadata": {
                  "usage.sample-usage": 2
                }
              },
              {
                "pos_only_required": {
                  "_0": {
                    "type": {
                      "module": "numpy",
                      "name": "ndarray"
                    }
                  }
                },
                "metadata": {
                  "usage.sample-usage": 1
                }
              },
              {
                "pos_only_required": {
                  "_0": {
                    "type": "slice",
                    "start": {
                      "type": {
                        "name": "int"
                      }
                    },
                    "stop": {
                      "type": {
                        "name": "int"
                      }
                    },
                    "step": {
                      "type": "None"
                    }
                  }
                },
                "metadata": {
                  "usage.sample-usage": 1
                }
              },
              {
                "pos_only_required": {
                  "_0": {
                    "type": "tuple",
                    "items": [
                      {
                        "type": "tuple",
                        "items": [
                          {
                            "type": {
                              "name": "int"
                            }
                          },
                          {
                            "type": {
                              "name": "int"
                            }
                          },
                          {
                            "type": {
                              "name": "int"
                            }
                          }
                        ]
                      },
                      {
                        "type": "tuple",
                        "items": [
                          {
                            "type": {
                              "name": "int"
                            }
                          },
                          {
                            "type": {
                              "name": "int"
                            }
                          },
                          {
                            "type": {
                              "name": "int"
                            }
                          }
                        ]
                      }
                    ]
                  }
                },
                "metadata": {
                  "usage.sample-usage": 1
                }
              }
            ],
            "__pow__": [
              {
                "pos_only_required": {
                  "_0": {
                    "type": {
                      "name": "int"
                    }
                  }
                },
                "metadata": {
                  "usage.sample-usage": 1
                }
              }
            ],
            "__rpow__": [
              {
                "pos_only_required": {
                  "_0": {
                    "type": {
                      "name": "int"
                    }
                  }
                },
                "metadata": {
                  "usage.sample-usage": 2
                }
              }
            ],
            "__mul__": [
              {
                "pos_only_required": {
                  "_0": {
                    "type": {
                      "name": "int"
                    }
                  }
                },
                "metadata": {
                  "usage.sample-usage": 1
                }
              }
            ],
            "__rmul__": [
              {
                "pos_only_required": {
                  "_0": {
                    "type": {
                      "name": "int"
                    }
                  }
                },
                "metadata": {
                  "usage.sample-usage": 2
                }
              }
            ],
            "__matmul__": [
              {
                "pos_only_required": {
                  "_0": {
                    "type": {
                      "module": "numpy",
                      "name": "ndarray"
                    }
                  }
                },
                "metadata": {
                  "usage.sample-usage": 1
                }
              }
            ],
            "__rmatmul__": [
              {
                "pos_only_required": {
                  "_0": {
                    "type": {
                      "module": "numpy",
                      "name": "ndarray"
                    }
                  }
                },
                "metadata": {
                  "usage.sample-usage": 1
                }
              }
            ],
            "__floordiv__": [
              {
                "pos_only_required": {
                  "_0": {
                    "type": {
                      "name": "int"
                    }
                  }
                },
                "metadata": {
                  "usage.sample-usage": 1
                }
              }
            ],
            "__rfloordiv__": [
              {
                "pos_only_required": {
                  "_0": {
                    "type": {
                      "name": "int"
                    }
                  }
                },
                "metadata": {
                  "usage.sample-usage": 1
                }
              }
            ],
            "__mod__": [
              {
                "pos_only_required": {
                  "_0": {
                    "type": {
                      "name": "int"
                    }
                  }
                },
                "metadata": {
                  "usage.sample-usage": 1
                }
              }
            ],
            "__rmod__": [
              {
                "pos_only_required": {
                  "_0": {
                    "type": {
                      "name": "int"
                    }
                  }
                },
                "metadata": {
                  "usage.sample-usage": 1
                }
              }
            ],
            "__add__": [
              {
                "pos_only_required": {
                  "_0": {
                    "type": {
                      "name": "int"
                    }
                  }
                },
                "metadata": {
                  "usage.sample-usage": 1
                }
              },
              {
                "pos_only_required": {
                  "_0": {
                    "type": {
                      "module": "numpy",
                      "name": "ndarray"
                    }
                  }
                },
                "metadata": {
                  "usage.sample-usage": 1
                }
              }
            ],
            "__radd__": [
              {
                "pos_only_required": {
                  "_0": {
                    "type": {
                      "name": "int"
                    }
                  }
                },
                "metadata": {
                  "usage.sample-usage": 1
                }
              },
              {
                "pos_only_required": {
                  "_0": {
                    "type": {
                      "module": "numpy",
                      "name": "ndarray"
                    }
                  }
                },
                "metadata": {
                  "usage.sample-usage": 1
                }
              }
            ],
            "__sub__": [
              {
                "pos_only_required": {
                  "_0": {
                    "type": {
                      "name": "int"
                    }
                  }
                },
                "metadata": {
                  "usage.sample-usage": 1
                }
              }
            ],
            "__rsub__": [
              {
                "pos_only_required": {
                  "_0": {
                    "type": {
                      "name": "int"
                    }
                  }
                },
                "metadata": {
                  "usage.sample-usage": 1
                }
              }
            ],
            "__lshift__": [
              {
                "pos_only_required": {
                  "_0": {
                    "type": {
                      "name": "int"
                    }
                  }
                },
                "metadata": {
                  "usage.sample-usage": 1
                }
              }
            ],
            "__rlshift__": [
              {
                "pos_only_required": {
                  "_0": {
                    "type": {
                      "name": "int"
                    }
                  }
                },
                "metadata": {
                  "usage.sample-usage": 1
                }
              }
            ],
            "__rshift__": [
              {
                "pos_only_required": {
                  "_0": {
                    "type": {
                      "name": "int"
                    }
                  }
                },
                "metadata": {
                  "usage.sample-usage": 1
                }
              }
            ],
            "__rrshift__": [
              {
                "pos_only_required": {
                  "_0": {
                    "type": {
                      "name": "int"
                    }
                  }
                },
                "metadata": {
                  "usage.sample-usage": 1
                }
              }
            ],
            "__and__": [
              {
                "pos_only_required": {
                  "_0": {
                    "type": {
                      "name": "int"
                    }
                  }
                },
                "metadata": {
                  "usage.sample-usage": 1
                }
              }
            ],
            "__rand__": [
              {
                "pos_only_required": {
                  "_0": {
                    "type": {
                      "name": "int"
                    }
                  }
                },
                "metadata": {
                  "usage.sample-usage": 1
                }
              }
            ],
            "__or__": [
              {
                "pos_only_required": {
                  "_0": {
                    "type": {
                      "name": "int"
                    }
                  }
                },
                "metadata": {
                  "usage.sample-usage": 1
                }
              }
            ],
            "__ror__": [
              {
                "pos_only_required": {
                  "_0": {
                    "type": {
                      "name": "int"
                    }
                  }
                },
                "metadata": {
                  "usage.sample-usage": 1
                }
              }
            ],
            "__ipow__": [
              {
                "pos_only_required": {
                  "_0": {
                    "type": {
                      "name": "int"
                    }
                  }
                },
                "metadata": {
                  "usage.sample-usage": 1
                }
              }
            ],
            "__imul__": [
              {
                "pos_only_required": {
                  "_0": {
                    "type": {
                      "name": "int"
                    }
                  }
                },
                "metadata": {
                  "usage.sample-usage": 1
                }
              }
            ],
            "__ifloordiv__": [
              {
                "pos_only_required": {
                  "_0": {
                    "type": {
                      "name": "int"
                    }
                  }
                },
                "metadata": {
                  "usage.sample-usage": 1
                }
              }
            ],
            "__imod__": [
              {
                "pos_only_required": {
                  "_0": {
                    "type": {
                      "name": "int"
                    }
                  }
                },
                "metadata": {
                  "usage.sample-usage": 1
                }
              }
            ],
            "__iadd__": [
              {
                "pos_only_required": {
                  "_0": {
                    "type": {
                      "name": "int"
                    }
                  }
                },
                "metadata": {
                  "usage.sample-usage": 1
                }
              }
            ],
            "__isub__": [
              {
                "pos_only_required": {
                  "_0": {
                    "type": {
                      "name": "int"
                    }
                  }
                },
                "metadata": {
                  "usage.sample-usage": 1
                }
              }
            ],
            "__ilshift__": [
              {
                "pos_only_required": {
                  "_0": {
                    "type": {
                      "name": "int"
                    }
                  }
                },
                "metadata": {
                  "usage.sample-usage": 1
                }
              }
            ],
            "__irshift__": [
              {
                "pos_only_required": {
                  "_0": {
                    "type": {
                      "name": "int"
                    }
                  }
                },
                "metadata": {
                  "usage.sample-usage": 1
                }
              }
            ],
            "__iand__": [
              {
                "pos_only_required": {
                  "_0": {
                    "type": {
                      "name": "int"
                    }
                  }
                },
                "metadata": {
                  "usage.sample-usage": 1
                }
              }
            ],
            "__ior__": [
              {
                "pos_only_required": {
                  "_0": {
                    "type": {
                      "name": "int"
                    }
                  }
                },
                "metadata": {
                  "usage.sample-usage": 1
                }
              }
            ],
            "__setitem__": [
              {
                "pos_only_required": {
                  "_0": {
                    "type": {
                      "name": "int"
                    }
                  },
                  "_1": {
                    "type": {
                      "name": "int"
                    }
                  }
                },
                "metadata": {
                  "usage.sample-usage": 1
                }
              }
            ],
            "mean": [
              {
                "metadata": {
                  "usage.sample-usage": 2
                }
              }
            ],
            "__eq__": [
              {
                "pos_only_required": {
                  "_0": {
                    "type": {
                      "module": "numpy",
                      "name": "ndarray"
                    }
                  }
                },
                "metadata": {
                  "usage.sample-usage": 2
                }
              }
            ],
            "__lt__": [
              {
                "pos_only_required": {
                  "_0": {
                    "type": {
                      "name": "int"
                    }
                  }
                },
                "metadata": {
                  "usage.sample-usage": 1
                }
              }
            ],
            "sort": [
              {
                "metadata": {
                  "usage.sample-usage": 1
                }
              },
              {
                "kw_only_required": {
                  "axis": {
                    "type": {
                      "name": "int"
                    }
                  }
                },
                "metadata": {
                  "usage.sample-usage": 1
                }
              }
            ],
            "__gt__": [
              {
                "pos_only_required": {
                  "_0": {
                    "type": {
                      "name": "int"
                    }
                  }
                },
                "metadata": {
                  "usage.sample-usage": 1
                }
              }
            ],
            "reshape": [
              {
                "pos_only_required": {
                  "_0": {
                    "type": {
                      "name": "int"
                    }
                  },
                  "_1": {
                    "type": {
                      "name": "int"
                    }
                  }
                },
                "metadata": {
                  "usage.sample-usage": 1
                }
              },
              {
                "pos_only_required": {
                  "_0": {
                    "type": "tuple",
                    "items": [
                      {
                        "type": {
                          "name": "int"
                        }
                      },
                      {
                        "type": {
                          "name": "int"
                        }
                      }
                    ]
                  }
                },
                "metadata": {
                  "usage.sample-usage": 1
                }
              }
            ],
            "astype": [
              {
                "pos_only_required": {
                  "_0": {
                    "type": "type",
                    "name": {
                      "name": "int"
                    }
                  }
                },
                "metadata": {
                  "usage.sample-usage": 1
                }
              }
            ],
            "__contains__": [
              {
                "pos_only_required": {
                  "_0": {
                    "type": {
                      "name": "int"
                    }
                  }
                },
                "metadata": {
                  "usage.sample-usage": 1
                }
              }
            ]
          },
          "methods": {
            "__pos__": {
              "metadata": {
                "usage.sample-usage": 1
              }
            },
            "__neg__": {
              "metadata": {
                "usage.sample-usage": 1
              }
            },
            "__invert__": {
              "metadata": {
                "usage.sample-usage": 1
              }
            },
            "__bool__": {
              "metadata": {
                "usage.sample-usage": 1
              }
            },
            "__iter__": {
              "metadata": {
                "usage.sample-usage": 2
              }
            },
            "__getitem__": {
              "pos_only_required": {
                "_0": {
                  "type": "union",
                  "options": [
                    {
                      "type": "tuple",
                      "items": [
                        {
                          "type": "tuple",
                          "items": [
                            {
                              "type": {
                                "name": "int"
                              }
                            },
                            {
                              "type": {
                                "name": "int"
                              }
                            },
                            {
                              "type": {
                                "name": "int"
                              }
                            }
                          ]
                        },
                        {
                          "type": "tuple",
                          "items": [
                            {
                              "type": {
                                "name": "int"
                              }
                            },
                            {
                              "type": {
                                "name": "int"
                              }
                            },
                            {
                              "type": {
                                "name": "int"
                              }
                            }
                          ]
                        }
                      ]
                    },
                    {
                      "type": {
                        "module": "numpy",
                        "name": "ndarray"
                      }
                    },
                    {
                      "type": {
                        "name": "int"
                      }
                    },
                    {
                      "type": "slice",
                      "start": {
                        "type": {
                          "name": "int"
                        }
                      },
                      "stop": {
                        "type": {
                          "name": "int"
                        }
                      },
                      "step": {
                        "type": "None"
                      }
                    }
                  ]
                }
              },
              "metadata": {
                "usage.sample-usage": 5
              }
            },
            "__pow__": {
              "pos_only_required": {
                "_0": {
                  "type": {
                    "name": "int"
                  }
                }
              },
              "metadata": {
                "usage.sample-usage": 1
              }
            },
            "__rpow__": {
              "pos_only_required": {
                "_0": {
                  "type": {
                    "name": "int"
                  }
                }
              },
              "metadata": {
                "usage.sample-usage": 2
              }
            },
            "__mul__": {
              "pos_only_required": {
                "_0": {
                  "type": {
                    "name": "int"
                  }
                }
              },
              "metadata": {
                "usage.sample-usage": 1
              }
            },
            "__rmul__": {
              "pos_only_required": {
                "_0": {
                  "type": {
                    "name": "int"
                  }
                }
              },
              "metadata": {
                "usage.sample-usage": 2
              }
            },
            "__matmul__": {
              "pos_only_required": {
                "_0": {
                  "type": {
                    "module": "numpy",
                    "name": "ndarray"
                  }
                }
              },
              "metadata": {
                "usage.sample-usage": 1
              }
            },
            "__rmatmul__": {
              "pos_only_required": {
                "_0": {
                  "type": {
                    "module": "numpy",
                    "name": "ndarray"
                  }
                }
              },
              "metadata": {
                "usage.sample-usage": 1
              }
            },
            "__floordiv__": {
              "pos_only_required": {
                "_0": {
                  "type": {
                    "name": "int"
                  }
                }
              },
              "metadata": {
                "usage.sample-usage": 1
              }
            },
            "__rfloordiv__": {
              "pos_only_required": {
                "_0": {
                  "type": {
                    "name": "int"
                  }
                }
              },
              "metadata": {
                "usage.sample-usage": 1
              }
            },
            "__mod__": {
              "pos_only_required": {
                "_0": {
                  "type": {
                    "name": "int"
                  }
                }
              },
              "metadata": {
                "usage.sample-usage": 1
              }
            },
            "__rmod__": {
              "pos_only_required": {
                "_0": {
                  "type": {
                    "name": "int"
                  }
                }
              },
              "metadata": {
                "usage.sample-usage": 1
              }
            },
            "__add__": {
              "pos_only_required": {
                "_0": {
                  "type": "union",
                  "options": [
                    {
                      "type": {
                        "module": "numpy",
                        "name": "ndarray"
                      }
                    },
                    {
                      "type": {
                        "name": "int"
                      }
                    }
                  ]
                }
              },
              "metadata": {
                "usage.sample-usage": 2
              }
            },
            "__radd__": {
              "pos_only_required": {
                "_0": {
                  "type": "union",
                  "options": [
                    {
                      "type": {
                        "module": "numpy",
                        "name": "ndarray"
                      }
                    },
                    {
                      "type": {
                        "name": "int"
                      }
                    }
                  ]
                }
              },
              "metadata": {
                "usage.sample-usage": 2
              }
            },
            "__sub__": {
              "pos_only_required": {
                "_0": {
                  "type": {
                    "name": "int"
                  }
                }
              },
              "metadata": {
                "usage.sample-usage": 1
              }
            },
            "__rsub__": {
              "pos_only_required": {
                "_0": {
                  "type": {
                    "name": "int"
                  }
                }
              },
              "metadata": {
                "usage.sample-usage": 1
              }
            },
            "__lshift__": {
              "pos_only_required": {
                "_0": {
                  "type": {
                    "name": "int"
                  }
                }
              },
              "metadata": {
                "usage.sample-usage": 1
              }
            },
            "__rlshift__": {
              "pos_only_required": {
                "_0": {
                  "type": {
                    "name": "int"
                  }
                }
              },
              "metadata": {
                "usage.sample-usage": 1
              }
            },
            "__rshift__": {
              "pos_only_required": {
                "_0": {
                  "type": {
                    "name": "int"
                  }
                }
              },
              "metadata": {
                "usage.sample-usage": 1
              }
            },
            "__rrshift__": {
              "pos_only_required": {
                "_0": {
                  "type": {
                    "name": "int"
                  }
                }
              },
              "metadata": {
                "usage.sample-usage": 1
              }
            },
            "__and__": {
              "pos_only_required": {
                "_0": {
                  "type": {
                    "name": "int"
                  }
                }
              },
              "metadata": {
                "usage.sample-usage": 1
              }
            },
            "__rand__": {
              "pos_only_required": {
                "_0": {
                  "type": {
                    "name": "int"
                  }
                }
              },
              "metadata": {
                "usage.sample-usage": 1
              }
            },
            "__or__": {
              "pos_only_required": {
                "_0": {
                  "type": {
                    "name": "int"
                  }
                }
              },
              "metadata": {
                "usage.sample-usage": 1
              }
            },
            "__ror__": {
              "pos_only_required": {
                "_0": {
                  "type": {
                    "name": "int"
                  }
                }
              },
              "metadata": {
                "usage.sample-usage": 1
              }
            },
            "__ipow__": {
              "pos_only_required": {
                "_0": {
                  "type": {
                    "name": "int"
                  }
                }
              },
              "metadata": {
                "usage.sample-usage": 1
              }
            },
            "__imul__": {
              "pos_only_required": {
                "_0": {
                  "type": {
                    "name": "int"
                  }
                }
              },
              "metadata": {
                "usage.sample-usage": 1
              }
            },
            "__ifloordiv__": {
              "pos_only_required": {
                "_0": {
                  "type": {
                    "name": "int"
                  }
                }
              },
              "metadata": {
                "usage.sample-usage": 1
              }
            },
            "__imod__": {
              "pos_only_required": {
                "_0": {
                  "type": {
                    "name": "int"
                  }
                }
              },
              "metadata": {
                "usage.sample-usage": 1
              }
            },
            "__iadd__": {
              "pos_only_required": {
                "_0": {
                  "type": {
                    "name": "int"
                  }
                }
              },
              "metadata": {
                "usage.sample-usage": 1
              }
            },
            "__isub__": {
              "pos_only_required": {
                "_0": {
                  "type": {
                    "name": "int"
                  }
                }
              },
              "metadata": {
                "usage.sample-usage": 1
              }
            },
            "__ilshift__": {
              "pos_only_required": {
                "_0": {
                  "type": {
                    "name": "int"
                  }
                }
              },
              "metadata": {
                "usage.sample-usage": 1
              }
            },
            "__irshift__": {
              "pos_only_required": {
                "_0": {
                  "type": {
                    "name": "int"
                  }
                }
              },
              "metadata": {
                "usage.sample-usage": 1
              }
            },
            "__iand__": {
              "pos_only_required": {
                "_0": {
                  "type": {
                    "name": "int"
                  }
                }
              },
              "metadata": {
                "usage.sample-usage": 1
              }
            },
            "__ior__": {
              "pos_only_required": {
                "_0": {
                  "type": {
                    "name": "int"
                  }
                }
              },
              "metadata": {
                "usage.sample-usage": 1
              }
            },
            "__setitem__": {
              "pos_only_required": {
                "_0": {
                  "type": {
                    "name": "int"
                  }
                },
                "_1": {
                  "type": {
                    "name": "int"
                  }
                }
              },
              "metadata": {
                "usage.sample-usage": 1
              }
            },
            "mean": {
              "metadata": {
                "usage.sample-usage": 2
              }
            },
            "__eq__": {
              "pos_only_required": {
                "_0": {
                  "type": {
                    "module": "numpy",
                    "name": "ndarray"
                  }
                }
              },
              "metadata": {
                "usage.sample-usage": 2
              }
            },
            "__lt__": {
              "pos_only_required": {
                "_0": {
                  "type": {
                    "name": "int"
                  }
                }
              },
              "metadata": {
                "usage.sample-usage": 1
              }
            },
            "sort": {
              "kw_only_optional": {
                "axis": {
                  "type": {
                    "name": "int"
                  }
                }
              },
              "metadata": {
                "usage.sample-usage": 2
              }
            },
            "__gt__": {
              "pos_only_required": {
                "_0": {
                  "type": {
                    "name": "int"
                  }
                }
              },
              "metadata": {
                "usage.sample-usage": 1
              }
            },
            "reshape": {
              "pos_only_required": {
                "_0": {
                  "type": "union",
                  "options": [
                    {
                      "type": "tuple",
                      "items": [
                        {
                          "type": {
                            "name": "int"
                          }
                        },
                        {
                          "type": {
                            "name": "int"
                          }
                        }
                      ]
                    },
                    {
                      "type": {
                        "name": "int"
                      }
                    }
                  ]
                }
              },
              "pos_only_optional": {
                "_1": {
                  "type": {
                    "name": "int"
                  }
                }
              },
              "metadata": {
                "usage.sample-usage": 2
              }
            },
            "astype": {
              "pos_only_required": {
                "_0": {
                  "type": "type",
                  "name": {
                    "name": "int"
                  }
                }
              },
              "metadata": {
                "usage.sample-usage": 1
              }
            },
            "__contains__": {
              "pos_only_required": {
                "_0": {
                  "type": {
                    "name": "int"
                  }
                }
              },
              "metadata": {
                "usage.sample-usage": 1
              }
            }
          },
          "properties": {
            "shape": [
              {
                "usage.sample-usage": 2
              },
              {
                "type": "tuple",
                "items": [
                  {
                    "type": {
                      "name": "int"
                    }
                  },
                  {
                    "type": {
                      "name": "int"
                    }
                  }
                ]
              }
            ],
            "ndim": [
              {
                "usage.sample-usage": 1
              },
              {
                "type": "bottom"
              }
            ],
            "dtype": [
              {
                "usage.sample-usage": 1
              },
              {
                "type": "bottom"
              }
            ],
            "size": [
              {
                "usage.sample-usage": 1
              },
              {
                "type": "bottom"
              }
            ],
            "T": [
              {
                "usage.sample-usage": 1
              },
              {
                "type": "bottom"
              }
            ]
          }
        },
        "dtype": {
          "constructor_overloads": [
            {
              "pos_only_required": {
                "_0": {
                  "type": "type",
                  "name": {
                    "module": "numpy",
                    "name": "int16"
                  }
                }
              },
              "metadata": {
                "usage.sample-usage": 1
              }
            }
          ],
          "constructor": {
            "pos_only_required": {
              "_0": {
                "type": "type",
                "name": {
                  "module": "numpy",
                  "name": "int16"
                }
              }
            },
            "metadata": {
              "usage.sample-usage": 1
            }
          }
        },
        "ufunc": {
          "method_overloads": {
            "__call__": [
              {
                "pos_only_required": {
                  "_0": {
                    "type": {
                      "module": "numpy",
                      "name": "ndarray"
                    }
                  },
                  "_1": {
                    "type": {
                      "module": "numpy",
                      "name": "ndarray"
                    }
                  }
                },
                "metadata": {
                  "usage.sample-usage": 1
                }
              },
              {
                "pos_only_required": {
                  "_0": {
                    "type": {
                      "module": "numpy",
                      "name": "ndarray"
                    }
                  }
                },
                "metadata": {
                  "usage.sample-usage": 2
                }
              }
            ],
            "reduce": [
              {
                "pos_only_required": {
                  "_0": {
                    "type": {
                      "module": "numpy",
                      "name": "ndarray"
                    }
                  }
                },
                "metadata": {
                  "usage.sample-usage": 1
                }
              }
            ]
          },
          "methods": {
            "__call__": {
              "pos_only_required": {
                "_0": {
                  "type": {
                    "module": "numpy",
                    "name": "ndarray"
                  }
                }
              },
              "pos_only_optional": {
                "_1": {
                  "type": {
                    "module": "numpy",
                    "name": "ndarray"
                  }
                }
              },
              "metadata": {
                "usage.sample-usage": 3
              }
            },
            "reduce": {
              "pos_only_required": {
                "_0": {
                  "type": {
                    "module": "numpy",
                    "name": "ndarray"
                  }
                }
              },
              "metadata": {
                "usage.sample-usage": 1
              }
            }
          }
        },
        "int64": {
          "constructor_overloads": [
            {
              "pos_only_required": {
                "_0": {
                  "type": {
                    "name": "int"
                  }
                }
              },
              "metadata": {
                "usage.sample-usage": 1
              }
            }
          ],
          "constructor": {
            "pos_only_required": {
              "_0": {
                "type": {
                  "name": "int"
                }
              }
            },
            "metadata": {
              "usage.sample-usage": 1
            }
          }
        }
      },
      "properties": {
        "int16": [
          {
            "usage.sample-usage": 1
          },
          {
            "type": "bottom"
          }
        ],
        "add": [
          {
            "usage.sample-usage": 2
          },
          {
            "type": "numpy.ufunc",
            "name": "add"
          }
        ],
        "exp": [
          {
            "usage.sample-usage": 1
          },
          {
            "type": "numpy.ufunc",
            "name": "exp"
          }
        ],
        "log": [
          {
            "usage.sample-usage": 1
          },
          {
            "type": "numpy.ufunc",
            "name": "log"
          }
        ]
      }
    },
    "numpy.random": {},
    "numpy.random.mtrand": {
      "classes": {
        "RandomState": {
          "constructor_overloads": [
            {
              "pos_only_required": {
                "_0": {
                  "type": {
                    "name": "int"
                  }
                }
              },
              "metadata": {
                "usage.sample-usage": 1
              }
            }
          ],
          "method_overloads": {
            "random": [
              {
                "metadata": {
                  "usage.sample-usage": 1
                }
              }
            ]
          },
          "methods": {
            "random": {
              "metadata": {
                "usage.sample-usage": 1
              }
            }
          }
        }
      }
    },
    "numpy.polynomial": {},
    "numpy.polynomial.chebyshev": {
      "classes": {
        "Chebyshev": {
          "classmethod_overloads": {
            "basis": [
              {
                "pos_or_kw_required": {
                  "deg": {
                    "type": {
                      "name": "int"
                    }
                  }
                },
                "metadata": {
                  "usage.sample-usage": 1
                }
              }
            ]
          },
          "classmethods": {
            "basis": {
              "pos_or_kw_required": {
                "deg": {
                  "type": {
                    "name": "int"
                  }
                }
              },
              "metadata": {
                "usage.sample-usage": 1
              }
            }
          }
        }
      }
    }
  }
}